{
  "slug": "qof-religions-oracle-query-drift",
  "capturedAt": "2026-03-07T11:31:08.525Z",
  "viewport": "1440x960",
  "fullPage": false,
  "status": "different",
  "note": "Compare religion milestone against pre-port oracle-query local screenshot.",
  "local": {
    "label": "local",
    "url": "http://127.0.0.1:35475/ui/dummy/index.html",
    "selector": "[data-screenshot=\"ui-dummy-card\"]",
    "readySelector": "[data-screenshot=\"ui-dummy-card\"]",
    "browser": "firefox",
    "delayMs": 300,
    "staticRoot": ".",
    "staticPath": "/ui/dummy/index.html",
    "artifact": "local.png",
    "sha256": "aa7179eb78edaf263c091514854b9a39906222aed7f4a1b9c97dbf4a8978dd8c"
  },
  "reference": {
    "type": "baseline",
    "label": "approved-baseline",
    "url": null,
    "browser": null,
    "selector": null,
    "readySelector": null,
    "delayMs": null,
    "staticRoot": null,
    "staticPath": null,
    "artifact": "baseline.png",
    "sha256": "7764c9b2e06ba111ecaf31cf8cf8be34cc572c517f714cef58144dc7bc23841d"
  }
}
